tracera/__init__.py
tracera/__main__.py
tracera/__version__.py
tracera-0.0.1.dist-info/AUTHORS.txt
tracera-0.0.1.dist-info/LICENSE.txt
tracera-0.0.1.dist-info/METADATA
tracera-0.0.1.dist-info/WHEEL
tracera-0.0.1.dist-info/top_level.txt
tracera-0.0.1.dist-info/RECORD
